[
{
"name":"Accordion",
"muiDocumentation":"/material-ui/react-accordion/"
},
{
"name":"Alert",
"muiDocumentation":"/material-ui/react-alert"
},
{
"name":"AppBar:top",
"muiDocumentation":"/material-ui/react-app-bar/"
},
{
"name":"AppBar:bottom",
"muiDocumentation":"/material-ui/react-app-bar#bottom-app-bar/"
},
{
"name":"Autocomplete",
"muiDocumentation":"/material-ui/react-autocomplete"
},
{
"name":"Banner",
"muiDocumentation":"Composable"
},
{
"name":"Avatar",
"muiDocumentation":"/material-ui/react-avatar"
},
{
"name":"Badge",
"muiDocumentation":"/material-ui/react-badge"
},
{
"name":"BottomNavigation",
"muiDocumentation":"/material-ui/react-bottom-navigation/"
},
{
"name":"Breadcrumbs",
"muiDocumentation":"/material-ui/react-breadcrumbs"
},
{
"name":"Button",
"muiDocumentation":"/material-ui/react-button/"
},
{
"name":"FloatingActionButton",
"muiDocumentation":"/material-ui/react-floating-action-button"
},
{
"name":"ButtonGroup",
"muiDocumentation":"/material-ui/react-button-group"
},
{
"name":"Card",
"muiDocumentation":"/material-ui/react-card/"
},
{
"name":"Checkbox",
"muiDocumentation":"/material-ui/react-checkbox/"
},
{
"name":"Chip",
"muiDocumentation":"/material-ui/react-chip/"
},
{
"name":"DataGrid",
"muiDocumentation":"/x/react-data-grid/"
},
{
"name":"DatePickers",
"muiDocumentation":"/x/react-date-pickers/getting-started/"
},
{
"name":"Dialog",
"muiDocumentation":"/material-ui/react-dialog/"
},
{
"name":"Divider",
"muiDocumentation":"/material-ui/react-divider/"
},
{
"name":"Drawer",
"muiDocumentation":"/material-ui/react-drawer/"
},
{
"name":"Icons",
"muiDocumentation":"/material-ui/icons/"
},
{
"name":"ImageList",
"muiDocumentation":"/material-ui/react-image-list/"
},
{
"name":"Link",
"muiDocumentation":"/material-ui/react-link/"
},
{
"name":"List",
"muiDocumentation":"/material-ui/react-list/"
},
{
"name":"Masonry",
"muiDocumentation":"/material-ui/react-masonry/"
},
{
"name":"MaterialIcons",
"muiDocumentation":"/material-ui/material-icons/"
},
{
"name":"Menu",
"muiDocumentation":"/material-ui/react-menu/"
},
{
"name":"Modal",
"muiDocumentation":"/material-ui/react-modal/"
},
{
"name":"NavigationRail"
},
{
"name":"Pagination",
"muiDocumentation":"/material-ui/react-pagination/"
},
{
"name":"Paper",
"muiDocumentation":"/material-ui/react-paper/"
},
{
"name":"Progress",
"muiDocumentation":"/material-ui/react-progress/"
},
{
"name":"RadioGroup",
"muiDocumentation":"/material-ui/react-radio-button/"
},
{
"name":"Rating",
"muiDocumentation":"/material-ui/react-rating/"
},
{
"name":"Select",
"muiDocumentation":"/material-ui/react-select/"
},
{
"name":"Skeleton",
"muiDocumentation":"/material-ui/react-skeleton/"
},
{
"name":"Slider",
"muiDocumentation":"/material-ui/react-slider/"
},
{
"name":"Snackbar",
"muiDocumentation":"/material-ui/react-snackbar/"
},
{
"name":"SpeedDial",
"muiDocumentation":"/material-ui/react-speed-dial"
},
{
"name":"Stepper",
"muiDocumentation":"/material-ui/react-stepper/"
},
{
"name":"Switch",
"muiDocumentation":"/material-ui/react-switch/"
},
{
"name":"Table",
"muiDocumentation":"/material-ui/react-table/"
},
{
"name":"Tabs",
"muiDocumentation":"/material-ui/react-tabs/"
},
{
"name":"TextField",
"muiDocumentation":"/material-ui/react-text-field/"
},
{
"name":"Timeline",
"muiDocumentation":"/material-ui/react-timeline/"
},
{
"name":"ToggleButton",
"muiDocumentation":"/material-ui/react-toggle-button/"
},
{
"name":"Tooltip",
"muiDocumentation":"/material-ui/react-tooltip/"
},
{
"name":"TransferList",
"muiDocumentation":"/material-ui/react-transfer-list/"
},
{
"name":"TreeView",
"muiDocumentation":"/x/react-tree-view/"
},
{
"name":"Typography",
"muiDocumentation":"/material-ui/react-typography/"
}
]